{"data":{"siteSettings":{"__typename":"SiteSettings","siteConfiguration":{"__typename":"SiteConfiguration","title":"Forward thinking digital solutions.","description":"Solving digital challenges with forward-thinking, user-centric and bespoke solutions.","favicon":{"__typename":"AcfMediaItemConnectionEdge","node":{"__typename":"MediaItem","sourceUrl":"https://demo.saigondigital.dev/wp-content/uploads/2024/04/favicon-1.png"}},"openGraphImage":{"__typename":"AcfMediaItemConnectionEdge","node":{"__typename":"MediaItem","sourceUrl":"https://demo.saigondigital.dev/wp-content/uploads/2024/04/og.png"}},"siteUrl":"https://faustjs-demo-pi.vercel.app"}}},"loading":false,"networkStatus":7}